TracWikiNotification-0.4.3.dist-info/DESCRIPTION.rst
TracWikiNotification-0.4.3.dist-info/METADATA
TracWikiNotification-0.4.3.dist-info/RECORD
TracWikiNotification-0.4.3.dist-info/WHEEL
TracWikiNotification-0.4.3.dist-info/entry_points.txt
TracWikiNotification-0.4.3.dist-info/metadata.json
TracWikiNotification-0.4.3.dist-info/top_level.txt
WikiNotification/__init__.py
WikiNotification/admin.py
WikiNotification/listener.py
WikiNotification/notification.py
WikiNotification/web_ui.py
WikiNotification/templates/admin_config.html
WikiNotification/templates/admin_user_notifications.html
WikiNotification/templates/notification.html
WikiNotification/templates/notifications_forms.html
WikiNotification/templates/notifications_list.html
WikiNotification/templates/wiki_notification_email_template.txt
