Metadata-Version: 2.0
Name: TracWikiNotification
Version: 0.4.3
Summary: Trac Plugin to allow email notification of changes on wiki pages
Home-page: http://wikinotification.ufsoft.org
Author: Pedro Algarvio
Author-email: ufs@ufsoft.org
License: BSD
Download-URL: https://python.org/pypi/TracWikiNotification
Keywords: trac plugin wiki notification
Platform: OS Independent - Anywhere Python and Trac >=0.11 runs.
Classifier: Development Status :: 4 - Beta
Classifier: Environment :: Web Environment
Classifier: Framework :: Trac
Classifier: Intended Audience :: System Administrators
Classifier: License :: OSI Approved :: BSD License
Classifier: Operating System :: OS Independent
Classifier: Programming Language :: Python
Classifier: Topic :: Text Processing
Classifier: Topic :: Utilities
Classifier: Topic :: Internet :: WWW/HTTP
Classifier: Topic :: Internet :: WWW/HTTP :: Dynamic Content
Requires-Dist: Trac
